msna_sim/__init__.py
msna_sim/config.py
msna_sim/constants.py
msna_sim/dashboard.py
msna_sim/features.py
msna_sim/noise.py
msna_sim/simulator.py
msna_sim-0.1.2.dist-info/licenses/LICENSE
msna_sim-0.1.2.dist-info/METADATA
msna_sim-0.1.2.dist-info/WHEEL
msna_sim-0.1.2.dist-info/entry_points.txt
msna_sim-0.1.2.dist-info/top_level.txt
msna_sim-0.1.2.dist-info/RECORD
