Metadata-Version: 2.4
Name: msna-sim
Version: 0.1.2
Summary: A library for generating synthetic Muscle Sympathetic Nerve Activity (MSNA) data with realistic and physiologically accurate characteristics.
Home-page: https://github.com/ryanirl/msna-sim
Author: Ryan 'RyanIRL' Peters
Author-email: ryanirl@icloud.com
Project-URL: Bug Reports, https://github.com/ryanirl/msna-sim/issues
Project-URL: Source, https://github.com/ryanirl/msna-sim
Project-URL: Documentation, https://github.com/ryanirl/msna-sim/blob/main/SPECS.md
Keywords: msna,nerve activity,signal simulation,synthetic data,microneurography,cardiovascular,autonomic nervous system
Classifier: Development Status :: 5 - Production/Stable
Classifier: Intended Audience :: Developers
Classifier: Intended Audience :: Science/Research
Classifier: Intended Audience :: Healthcare Industry
Classifier: License :: OSI Approved :: MIT License
Classifier: Programming Language :: Python :: 3
Classifier: Programming Language :: Python :: 3.8
Classifier: Programming Language :: Python :: 3.9
Classifier: Programming Language :: Python :: 3.10
Classifier: Programming Language :: Python :: 3.11
Classifier: Programming Language :: Python :: 3.12
Classifier: Topic :: Scientific/Engineering
Classifier: Topic :: Scientific/Engineering :: Medical Science Apps.
Classifier: Topic :: Scientific/Engineering :: Bio-Informatics
Classifier: Topic :: Software Development :: Libraries :: Python Modules
Requires-Python: >=3.8
License-File: LICENSE
Requires-Dist: numpy>=1.19.0
Requires-Dist: pandas>=1.3.0
Requires-Dist: bokeh>=2.4.0
Requires-Dist: tornado>=6.0
Dynamic: author
Dynamic: author-email
Dynamic: classifier
Dynamic: description
Dynamic: description-content-type
Dynamic: home-page
Dynamic: keywords
Dynamic: license-file
Dynamic: project-url
Dynamic: requires-dist
Dynamic: requires-python
Dynamic: summary
